[
  {
    "DeniedAlternatives": [],
    "Files": {
      "objects/human/alertlight/alertlight.object": [
        "/hylotlDescription"
      ]
    },
    "Texts": {
      "Eng": "A clumsy dancing light."
    }
  },
  {
    "DeniedAlternatives": [],
    "Files": {
      "objects/human/alertlight/alertlight.object": [
        "/novakidDescription"
      ]
    },
    "Texts": {
      "Eng": "A light cravin' attention."
    }
  },
  {
    "DeniedAlternatives": [],
    "Files": {
      "objects/human/alertlight/alertlight.object": [
        "/shortdescription"
      ]
    },
    "Texts": {
      "Eng": "Alert Light"
    }
  },
  {
    "DeniedAlternatives": [],
    "Files": {
      "objects/human/alertlight/alertlight.object": [
        "/glitchDescription"
      ]
    },
    "Texts": {
      "Eng": "Neutral. A coloured light."
    }
  },
  {
    "DeniedAlternatives": [],
    "Files": {
      "objects/human/alertlight/alertlight.object": [
        "/floranDescription"
      ]
    },
    "Texts": {
      "Eng": "Ssswirling light. Like firefly in a jar."
    }
  },
  {
    "DeniedAlternatives": [],
    "Files": {
      "objects/human/alertlight/alertlight.object": [
        "/description"
      ]
    },
    "Texts": {
      "Eng": "The flashing light is meant to signal that there's been some sort of emergency..."
    }
  },
  {
    "DeniedAlternatives": [],
    "Files": {
      "objects/human/alertlight/alertlight.object": [
        "/avianDescription"
      ]
    },
    "Texts": {
      "Eng": "The machine, it squawks like a bird."
    }
  },
  {
    "DeniedAlternatives": [],
    "Files": {
      "objects/human/alertlight/alertlight.object": [
        "/apexDescription"
      ]
    },
    "Texts": {
      "Eng": "These alarms were common in Apex housing, signalling unacceptable behaviour."
    }
  },
  {
    "DeniedAlternatives": [],
    "Files": {
      "objects/human/alertlight/alertlight.object": [
        "/humanDescription"
      ]
    },
    "Texts": {
      "Eng": "These things scream danger."
    }
  }
]