[
  {
    "DeniedAlternatives": [],
    "Files": {
      "cinematics/story/opengate/opengate.cinematic": [
        "/panels/38/text"
      ]
    },
    "Texts": {
      "Eng": "Actually, we appear to not have any recorded data on the final artifact."
    }
  },
  {
    "DeniedAlternatives": [],
    "Files": {
      "cinematics/story/opengate/opengate.cinematic": [
        "/panels/39/text"
      ]
    },
    "Texts": {
      "Eng": "Correct. The reason being that it has been in our possession all along."
    }
  },
  {
    "DeniedAlternatives": [],
    "Files": {
      "cinematics/story/opengate/opengate.cinematic": [
        "/panels/41/text"
      ]
    },
    "Texts": {
      "Eng": "It is the original - the ^orange;Master Manipulator^white; - and it also happens to be the artifact gifted to the humans."
    }
  },
  {
    "DeniedAlternatives": [],
    "Files": {
      "cinematics/story/opengate/opengate.cinematic": [
        "/panels/36/text"
      ]
    },
    "Texts": {
      "Eng": "Only one artifact missssing now!"
    }
  },
  {
    "DeniedAlternatives": [],
    "Files": {
      "cinematics/story/opengate/opengate.cinematic": [
        "/panels/40/text"
      ]
    },
    "Texts": {
      "Eng": "This Matter Manipulator that I'm holding is the only one of its kind."
    }
  },
  {
    "DeniedAlternatives": [],
    "Files": {
      "cinematics/story/opengate/opengate.cinematic": [
        "/panels/37/text"
      ]
    },
    "Texts": {
      "Eng": "Yes, and according to our research..."
    }
  }
]