[
  {
    "DeniedAlternatives": [],
    "Files": {
      "items/materials/bookpiles.matitem": [
        "/description"
      ],
      "tiles/materials/bookpiles.material": [
        "/description"
      ]
    },
    "Texts": {
      "Eng": "A pile of dusty old books, they're full of tales of dragons and knights."
    }
  },
  {
    "DeniedAlternatives": [],
    "Files": {
      "items/materials/bookpiles.matitem": [
        "/glitchdescription"
      ],
      "tiles/materials/bookpiles.material": [
        "/glitchDescription"
      ]
    },
    "Texts": {
      "Eng": "Entertained. There are wonderful stories recorded inside these books."
    }
  },
  {
    "DeniedAlternatives": [],
    "Files": {
      "items/materials/bookpiles.matitem": [
        "/florandescription"
      ],
      "tiles/materials/bookpiles.material": [
        "/floranDescription"
      ]
    },
    "Texts": {
      "Eng": "Greatnesss not found in bookss."
    }
  },
  {
    "DeniedAlternatives": [],
    "Files": {
      "items/materials/bookpiles.matitem": [
        "/shortdescription"
      ],
      "tiles/materials/bookpiles.material": [
        "/shortdescription"
      ]
    },
    "Texts": {
      "Eng": "Pile of Books"
    }
  },
  {
    "DeniedAlternatives": [],
    "Files": {
      "items/materials/bookpiles.matitem": [
        "/novakiddescription"
      ],
      "tiles/materials/bookpiles.material": [
        "/novakidDescription"
      ]
    },
    "Texts": {
      "Eng": "Some dusty books. Who doesn't love t'hear a good story?"
    }
  }
]