[
  {
    "DeniedAlternatives": [],
    "Files": {
      "items/materials/supermatter.matitem": [
        "/novakiddescription"
      ],
      "tiles/materials/supermatter.material": [
        "/novakidDescription"
      ]
    },
    "Texts": {
      "Eng": "A big ol' erchius crystal."
    }
  },
  {
    "DeniedAlternatives": [],
    "Files": {
      "items/materials/supermatter.matitem": [
        "/description"
      ],
      "tiles/materials/supermatter.material": [
        "/description"
      ]
    },
    "Texts": {
      "Eng": "A crystal used to power FTL technology. It's still not fully understood."
    }
  },
  {
    "DeniedAlternatives": [],
    "Files": {
      "items/materials/supermatter.matitem": [
        "/shortdescription"
      ],
      "tiles/materials/supermatter.material": [
        "/shortdescription"
      ]
    },
    "Texts": {
      "Eng": "Erchius Crystal"
    }
  },
  {
    "DeniedAlternatives": [],
    "Files": {
      "items/materials/supermatter.matitem": [
        "/glitchdescription"
      ],
      "tiles/materials/supermatter.material": [
        "/glitchDescription"
      ]
    },
    "Texts": {
      "Eng": "Intrigued. Erchius crystals contain a mysterious power."
    }
  },
  {
    "DeniedAlternatives": [],
    "Files": {
      "items/materials/supermatter.matitem": [
        "/florandescription"
      ],
      "tiles/materials/supermatter.material": [
        "/floranDescription"
      ]
    },
    "Texts": {
      "Eng": "Shiny giant crystalss."
    }
  }
]